{"contract_payment.md":"25b0eb34","contract_release.md":"aed1f066","contract_bill-notice.md":"19c40333","contract_index.md":"e520edf8","document_index.md":"1e93ed6a","settings_details.md":"c662779d","settings_project.md":"2baaeb0d","settings_site-manage.md":"d7ef4b07","authority_admin-page.md":"183cb566","authority_index.md":"db44ea93","cashes_manage.md":"4f416b13","document_legal-case.md":"03d4fc4e","index.md":"cbd1989d","cashes_settings.md":"73918218","intro_getting-started.md":"ffe2eaf9","settings_company.md":"02450345"}
