{"document_index.md":"1bfa7bb1","authority_admin-page.md":"7774d931","authority_index.md":"105b9c11","cashes_manage.md":"a95c4e17","cashes_settings.md":"d8416f28","contract_bill-notice.md":"a74510cf","contract_index.md":"194b9d38","contract_payment.md":"eecfc771","contract_release.md":"4295b068","settings_company.md":"e31077c2","settings_details.md":"4494e181","settings_project.md":"3bb6b89c","settings_site-manage.md":"7c586560","document_legal-case.md":"56427d46","index.md":"10e73496","intro_getting-started.md":"b8aab823"}
