{"cashes_manage.md":"5dad4ac8","settings_project.md":"3672be70","authority_admin-page.md":"fe8074d3","intro_getting-started.md":"f22ee81c","settings_details.md":"52afebd5","authority_index.md":"174f4963","document_index.md":"9038badd","contract_bill-notice.md":"ede905ef","contract_index.md":"e17ac71c","contract_payment.md":"c001a9bc","settings_company.md":"fdd49df0","index.md":"f16a961c","document_legal-case.md":"15a1cb7a","contract_release.md":"5d67e0f1","cashes_settings.md":"1158215f","settings_site-manage.md":"d66a7756"}
