{"authority_admin-page.md":"60b2f3d1","authority_index.md":"a3aba619","cashes_manage.md":"1564f6a3","cashes_settings.md":"e8414236","contract_bill-notice.md":"8109a42e","contract_index.md":"3191d1b3","contract_payment.md":"f49084e7","contract_release.md":"0448b7f6","document_index.md":"2fbec4bb","document_legal-case.md":"aa857b03","index.md":"32a9175d","intro_getting-started.md":"1bbd0c73","settings_company.md":"0fcea58f","settings_details.md":"72fc7c99","settings_project.md":"0dd689d2","settings_site-manage.md":"67ebdfc2"}
