{"authority_admin-page.md":"c24186b8","settings_details.md":"578a336e","authority_index.md":"38c1df1e","settings_company.md":"6feeb430","intro_getting-started.md":"deea11f5","cashes_settings.md":"68a88caf","cashes_manage.md":"0fca64e7","contract_bill-notice.md":"88d66ee4","settings_site-manage.md":"d55206aa","index.md":"f039af0a","settings_project.md":"d82f583f","document_index.md":"3eb2db54","document_legal-case.md":"74f4f00f","contract_release.md":"fba2ee8f","contract_index.md":"c92b49ba","contract_payment.md":"a265eafa"}
