{"authority_admin-page.md":"ea58f29b","authority_index.md":"b1ed64a1","cashes_manage.md":"30eade1a","cashes_settings.md":"f6d6fcf1","contract_bill-notice.md":"def14a18","contract_index.md":"f2d80b5f","contract_payment.md":"2cd23d0f","contract_release.md":"1a80f1f0","document_index.md":"173d512b","document_legal-case.md":"31a09380","index.md":"7243a374","intro_getting-started.md":"7b92534c","settings_company.md":"524bbf29","settings_details.md":"a747a78d","settings_project.md":"39668d16","settings_site-manage.md":"edde3af7"}
