{"contract_index.md":"69aca6cc","settings_details.md":"bbfc0a66","settings_project.md":"fece73c6","cashes_manage.md":"2e5fbc69","settings_site-manage.md":"8753f578","document_index.md":"0c0b8288","contract_bill-notice.md":"4d373e70","authority_index.md":"6193be16","intro_getting-started.md":"415b05e2","settings_company.md":"efe365c2","index.md":"cc530454","contract_release.md":"b01fa260","authority_admin-page.md":"13931f42","contract_payment.md":"efa0e507","document_legal-case.md":"ed0ff412","cashes_settings.md":"0f47c98c"}
