{"contract_bill-notice.md":"279f47fb","authority_index.md":"0bfad335","settings_site-manage.md":"10b3729c","settings_details.md":"f41ccd68","contract_index.md":"b691f076","contract_payment.md":"fc080c07","contract_release.md":"c6ab3293","document_index.md":"124fb0b7","settings_project.md":"75a9857c","document_legal-case.md":"13f49794","cashes_settings.md":"3b91e56a","authority_admin-page.md":"1be58eda","settings_company.md":"2b63959d","index.md":"1dd4d206","cashes_manage.md":"9cc0234c","intro_getting-started.md":"9aa5e7b3"}
