{"authority_admin-page.md":"d41afd68","authority_index.md":"87f4f1d0","cashes_manage.md":"2a0ebe7c","cashes_settings.md":"1b428a6d","contract_bill-notice.md":"7859afc3","contract_index.md":"59b7df54","contract_payment.md":"3be5e179","contract_release.md":"1f647efb","document_index.md":"364a7244","document_legal-case.md":"284cffcd","index.md":"18585316","intro_getting-started.md":"2a312089","settings_company.md":"7c6e5d8a","settings_details.md":"5236e7de","settings_project.md":"4d3608bf","settings_site-manage.md":"31bc5b3d"}
