{"cashes_manage.md":"88da6e5f","cashes_settings.md":"b64afefd","contract_bill-notice.md":"640f3c65","contract_index.md":"b498f0f8","authority_admin-page.md":"27ed0400","authority_index.md":"d156fa63","contract_payment.md":"70e79dec","document_index.md":"ee89543b","document_legal-case.md":"cdbd1382","index.md":"cad7402a","intro_getting-started.md":"a03a6e1a","settings_company.md":"7fd5523c","settings_details.md":"01e0b06f","settings_project.md":"2bfd33ab","settings_site-manage.md":"53b22962","contract_release.md":"3fb7f573"}
