{"document_index.md":"ab4c6b0c","settings_company.md":"42efcbce","authority_admin-page.md":"c882c3a2","document_legal-case.md":"d70c087f","index.md":"1cb51485","intro_getting-started.md":"60d4c47e","settings_site-manage.md":"39301cc4","settings_details.md":"ab64d7cf","settings_project.md":"82559fa9","contract_index.md":"4e959422","contract_release.md":"e5e4e7c4","contract_bill-notice.md":"fed18ff1","authority_index.md":"302c1859","cashes_manage.md":"f270b4b1","cashes_settings.md":"9350b7f5","contract_payment.md":"bb6a6dbb"}
