{"contract_bill-notice.md":"324b7962","settings_company.md":"5458f55e","cashes_manage.md":"e9f8f4b0","authority_admin-page.md":"30d46605","contract_index.md":"6bea0d58","settings_site-manage.md":"6ffd7764","authority_index.md":"7dab0352","document_legal-case.md":"3df96dd6","cashes_settings.md":"031bf88f","contract_payment.md":"d57a321b","intro_getting-started.md":"8d964720","document_index.md":"67a3af18","index.md":"558d845c","settings_details.md":"00cf58d9","settings_project.md":"20c3fba8","contract_release.md":"03d465bb"}
