{"authority_admin-page.md":"630bc4f0","authority_index.md":"ac514e83","cashes_manage.md":"f85c1a73","cashes_settings.md":"8c6bae3a","contract_bill-notice.md":"79c46c4d","contract_index.md":"21f639df","contract_payment.md":"97d4eab4","contract_release.md":"9a292bdc","document_index.md":"caa14bb0","document_legal-case.md":"40774e0a","index.md":"9aaa0339","intro_getting-started.md":"e612d24d","settings_company.md":"fec4f2e7","settings_details.md":"3e1e47b8","settings_project.md":"d41774fa","settings_site-manage.md":"d6b85423"}
