{"authority_admin-page.md":"3cda7cf0","authority_index.md":"b31e233e","cashes_manage.md":"50a639e4","cashes_settings.md":"e21973a0","contract_bill-notice.md":"f1a62db7","contract_index.md":"8e17c856","contract_payment.md":"d93fe963","contract_release.md":"689bff2a","document_index.md":"0fbc02e1","document_legal-case.md":"69e0ac61","index.md":"55f458de","intro_getting-started.md":"e06d66aa","settings_company.md":"81a5fdda","settings_details.md":"9c7a8dd1","settings_project.md":"b4fbcf69","settings_site-manage.md":"b102123e"}
