{"cashes_settings.md":"83635ecc","contract_bill-notice.md":"76fa129b","contract_index.md":"3d7a1a9a","contract_payment.md":"2525f519","authority_index.md":"2b9e2f2a","contract_release.md":"73e823a5","cashes_manage.md":"ef02d65e","authority_admin-page.md":"f3e060c5","document_index.md":"5fafb16b","settings_details.md":"ca597eac","settings_project.md":"241e0363","index.md":"209fddf8","document_legal-case.md":"7ed5cc1c","intro_getting-started.md":"019adeba","settings_site-manage.md":"bf27547d","settings_company.md":"836ea4bf"}
