{"authority_admin-page.md":"1432371c","settings_details.md":"620f9871","contract_bill-notice.md":"7ac4f9e1","cashes_settings.md":"5fdd40b7","authority_index.md":"4610bf66","settings_site-manage.md":"ee3a3c3d","intro_getting-started.md":"d9b9d1d9","contract_index.md":"c743990f","contract_payment.md":"a0985f9c","settings_project.md":"d18c7112","index.md":"767cb712","contract_release.md":"74094251","document_legal-case.md":"80c01588","document_index.md":"6eb7fe87","cashes_manage.md":"3773968d","settings_company.md":"7c317040"}
