{"settings_site-manage.md":"6332d427","document_index.md":"0c824997","authority_admin-page.md":"28599912","settings_company.md":"7f715a18","settings_project.md":"a7d11606","settings_details.md":"c260614e","cashes_manage.md":"18e29046","authority_index.md":"fb2942bc","contract_bill-notice.md":"2ffd7844","cashes_settings.md":"ae13a676","contract_payment.md":"fd415bad","contract_index.md":"436f0f5b","contract_release.md":"beb9da48","intro_getting-started.md":"5369c0e8","document_legal-case.md":"7482c4c0","index.md":"0cd5d858"}
