{"contract_index.md":"f4f0cae3","document_index.md":"d2fea646","authority_index.md":"09dd796f","index.md":"6a5e6496","document_legal-case.md":"c795247c","intro_getting-started.md":"23f57c34","cashes_settings.md":"61cc5d6e","contract_bill-notice.md":"494011d6","contract_release.md":"18e9d9a1","settings_details.md":"ff7c1456","settings_site-manage.md":"e4546d79","settings_company.md":"77940fd6","settings_project.md":"ba2bc6d9","contract_payment.md":"2727591d","authority_admin-page.md":"c6068e11","cashes_manage.md":"049604e1"}
