{"settings_company.md":"6a13f815","intro_getting-started.md":"3fac0f4b","settings_project.md":"3b8d80f7","settings_site-manage.md":"6c663409","contract_release.md":"1cfa6b4c","authority_admin-page.md":"2d086e69","authority_index.md":"1bc09c45","cashes_manage.md":"ec6dc1b8","contract_bill-notice.md":"742ffecb","contract_index.md":"99a67f8b","contract_payment.md":"076b86fe","document_index.md":"90280f32","document_legal-case.md":"5d1eda07","cashes_settings.md":"7ec24b3a","index.md":"8fd74d69","settings_details.md":"38b77474"}
