{"authority_admin-page.md":"3635d8fc","authority_index.md":"5596abb5","cashes_manage.md":"7f984381","cashes_settings.md":"8737e899","contract_bill-notice.md":"618f66f5","contract_index.md":"3c008606","contract_payment.md":"789eeaed","contract_release.md":"2abd5e4c","document_index.md":"f7d88295","document_legal-case.md":"04673576","index.md":"d92900d3","intro_getting-started.md":"339ba7ba","settings_company.md":"6780edf1","settings_details.md":"fe9221bd","settings_project.md":"6984d18f","settings_site-manage.md":"a62256a9"}
